[
  {
    "inputs": [
      {
        "internalType": "address",
        "name": "soulboundStorage",
        "type": "address"
      }
    ],
    "stateMutability": "nonpayable",
    "type": "constructor"
  },
  {
    "inputs": [
      {
        "internalType": "string",
        "name": "name",
        "type": "string"
      },
      {
        "internalType": "string",
        "name": "symbol",
        "type": "string"
      },
      {
        "internalType": "string",
        "name": "uri",
        "type": "string"
      }
    ],
    "name": "createCollection",
    "outputs": [
      {
        "internalType": "address",
        "name": "",
        "type": "address"
      }
    ],
    "stateMutability": "nonpayable",
    "type": "function"
  }
]
